mapping_shortcuts/__init__.py
mapping_shortcuts/decors.py
mapping_shortcuts/dirtools.py
mapping_shortcuts/meta.py
mapping_shortcuts/utils.py
mapping_shortcuts/cli/__init__.py
mapping_shortcuts/cli/cli.py
mapping_shortcuts/cli/consts.py
mapping_shortcuts/cli/help.py
tests/__init__.py
tests/__main__.py
tests/decors.py
tests/meta.py
tests/utils.py
tests/cli/__init__.py
tests/cli/cli.py
mapping_shortcuts-1.2.1.dist-info/METADATA
mapping_shortcuts-1.2.1.dist-info/WHEEL
mapping_shortcuts-1.2.1.dist-info/top_level.txt
mapping_shortcuts-1.2.1.dist-info/RECORD
