Metadata-Version: 2.1
Name: mapping_shortcuts
Version: 1.2.1
Summary: Useful shortcuts for create mappings
Home-page: https://github.com/moff4/shortcuts
Author: Komissarov Andrey
Author-email: Komissar.off.andrey@gmail.com
Classifier: Programming Language :: Python :: 3.9
Classifier: Programming Language :: Python :: 3.10
Classifier: Operating System :: OS Independent
